underautomation/__init__.py
underautomation/fanuc/__init__.py
underautomation/fanuc/connection_parameters.py
underautomation/fanuc/fanuc_robot.py
underautomation/fanuc/common/__init__.py
underautomation/fanuc/common/arm_front_back.py
underautomation/fanuc/common/arm_left_right.py
underautomation/fanuc/common/arm_up_down.py
underautomation/fanuc/common/cartesian_position.py
underautomation/fanuc/common/cartesian_position_with_tool.py
underautomation/fanuc/common/cartesian_position_with_user_frame.py
underautomation/fanuc/common/configuration.py
underautomation/fanuc/common/connect_exception.py
underautomation/fanuc/common/digital_ports.py
underautomation/fanuc/common/extended_cartesian_position.py
underautomation/fanuc/common/ftp_connect_parameters.py
underautomation/fanuc/common/io_status.py
underautomation/fanuc/common/joints_position.py
underautomation/fanuc/common/languages.py
underautomation/fanuc/common/position.py
underautomation/fanuc/common/program_type.py
underautomation/fanuc/common/rmi_connect_parameters.py
underautomation/fanuc/common/snpx_connect_parameters.py
underautomation/fanuc/common/stream_motion_connect_parameters.py
underautomation/fanuc/common/string_utils.py
underautomation/fanuc/common/task_status.py
underautomation/fanuc/common/telnet_connect_parameters.py
underautomation/fanuc/common/wrist_flip.py
underautomation/fanuc/common/xyz_position.py
underautomation/fanuc/ftp/__init__.py
underautomation/fanuc/ftp/fanuc_file_readers.py
underautomation/fanuc/ftp/ftp_client.py
underautomation/fanuc/ftp/ftp_file_system_object_type.py
underautomation/fanuc/ftp/ftp_list_item.py
underautomation/fanuc/ftp/diagnosis/__init__.py
underautomation/fanuc/ftp/diagnosis/current_position.py
underautomation/fanuc/ftp/diagnosis/current_position_reader.py
underautomation/fanuc/ftp/diagnosis/diagnosis_reader_2.py
underautomation/fanuc/ftp/diagnosis/feature.py
underautomation/fanuc/ftp/diagnosis/features.py
underautomation/fanuc/ftp/diagnosis/features_parser.py
underautomation_fanuc-4.0.0.0.dist-info/METADATA
underautomation_fanuc-4.0.0.0.dist-info/WHEEL
underautomation_fanuc-4.0.0.0.dist-info/top_level.txt
underautomation_fanuc-4.0.0.0.dist-info/RECORD
